geokel/BOLA1.py
geokel/Limas.py
geokel/__init__.py
geokel/kerucut.py
geokel/kubusBalok.py
geokel/prisma.py
geokel/tabung.py
geometri/BOLA1.py
geometri/Limas.py
geometri/__init__.py
geometri/kerucut.py
geometri/kubusBalok.py
geometri/prisma.py
geometri/tabung.py
geometri_package-0.1.4.dist-info/METADATA
geometri_package-0.1.4.dist-info/PKG-INFO-DESKTOP-9T51642
geometri_package-0.1.4.dist-info/SOURCES-DESKTOP-9T51642.txt
geometri_package-0.1.4.dist-info/WHEEL
geometri_package-0.1.4.dist-info/top_level-DESKTOP-9T51642.txt
geometri_package-0.1.4.dist-info/top_level.txt
geometri_package-0.1.4.dist-info/RECORD
