Metadata-Version: 2.1
Name: geometri-package
Version: 0.1.4
Summary: Paket untuk menghitung berbagai bangun ruang.
Home-page: https://github.com/nurulmarisa8/geometri-package.git
Author: Kelompok 4 ALGO A
Author-email: office@unhas.ac.id
License: MIT
